deepner/__init__.py
deepner/analysis.py
deepner/ner.json
deepner/ner.pb
deepner/resources/data/tags.txt
deepner/resources/data/vocab.txt
deepner-1.1.0.dist-info/DESCRIPTION.rst
deepner-1.1.0.dist-info/METADATA
deepner-1.1.0.dist-info/RECORD
deepner-1.1.0.dist-info/WHEEL
deepner-1.1.0.dist-info/entry_points.txt
deepner-1.1.0.dist-info/metadata.json
deepner-1.1.0.dist-info/top_level.txt
