Metadata-Version: 2.0
Name: deepner
Version: 1.1.0
Summary: Deep learning nlp model framework, provides command-line tools.
Home-page: UNKNOWN
Author: wangsihong
Author-email: wangsihong@live.com
License: GPLv3
Keywords: lstm-crf,crf,ner
Platform: any
Classifier: Development Status :: 4 - Beta
Classifier: Operating System :: OS Independent
Classifier: Intended Audience :: Developers
Classifier: License :: OSI Approved :: BSD License
Classifier: Programming Language :: Python
Classifier: Programming Language :: Python :: Implementation
Classifier: Programming Language :: Python :: 3
Classifier: Programming Language :: Python :: 3.6
Classifier: Topic :: Software Development :: Libraries
